LICENSE.md
MANIFEST.in
README.md
setup.py
core/__init__.py
core/index.py
core/interpreter/Interpreter.py
core/interpreter/__init__.py
core/tools/__init__.py
core/tools/createvirtualdom.py
core/tools/linebyline.py
core/tools/writetofile.py
simple_engine_core.egg-info/PKG-INFO
simple_engine_core.egg-info/SOURCES.txt
simple_engine_core.egg-info/dependency_links.txt
simple_engine_core.egg-info/entry_points.txt
simple_engine_core.egg-info/requires.txt
simple_engine_core.egg-info/top_level.txt
test/test.py