Metadata-Version: 1.0
Name: simple-engine-core
Version: 2.4
Summary: Reads in HTML, reads out JSON
Home-page: https://github.com/apizzimenti/simple-engine-core.git
Author: Anthony Pizzimenti
Author-email: pizzimentianthony@gmail.com
License: MIT
Platform: UNKNOWN
